[{"id":"VH916152","type":"mcq","stimulusHtml":"<p class=\"stem_paragraph\">In <span class=\"formatted_text font_style:italic\">Citizens United</span> v. <span class=\"formatted_text font_style:italic\">Federal Election Commission</span> (2010), the Supreme Court ruled that corporations and labor unions could spend unlimited amounts of money on political advertising. Which of the following was the basis for the Court’s ruling?</p>\n","rubricRef":"VH916152_rubric","choicesHtml":["<p class=\"choice_paragraph\">The freedom of assembly in the First Amendment</p>","<p class=\"choice_paragraph\">The freedom of speech in the First Amendment</p>","<p class=\"choice_paragraph\">The due process clause in the Fourteenth Amendment</p>","<p class=\"choice_paragraph\">The equal protection clause in the Fourteenth Amendment</p>"],"answer":1}]