[{"id":"VH900905","type":"mcq","stimulusHtml":"<div>\n<div class=\"stimulus_reference\">\n<div class=\"standalone_image\"><img alt=\"The figure presents a histogram with 7 bars of data. The horizontal axis is labeled Motel Occupancy Rate, and the numbers 0.60 through 0.95, in increments of 0.05, are indicated. The vertical axis is labeled Relative Frequency, and the numbers 0 through 0.35, in increments of 0.05, are indicated. The data represented by the bars are as follows. Note that all values are approximate. 0.60 through 0.65 percent occupancy, 0.30. 0.65 through 0.70 percent occupancy, 0.26. 0.70 through 0.75 percent occupancy, 0.23. 0.75 through 0.80 percent occupancy, 0.04. 0.80 through 0.85 percent occupancy, 0.04. 0.85 through 0.90 percent occupancy, 0.08. 0.90 through 0.95 percent occupancy, 0.06.\" height=\"207\" src=\"https://assets.learnosity.com/organisations/537/VH900905.g04.png\" width=\"400\" /></div>\n</div>\n</div>\n\n<p class=\"stem_paragraph\">The occupancy rate of a motel is the percentage of rooms that are occupied on a particular night. The histogram shown summarizes the occupancy rates for a random sample of 100 nights for a motel. Based on the histogram, which of the following best describes the shape of the distribution of occupancy rates?</p>\n","rubricRef":"VH900905_rubric","choicesHtml":["<p class=\"choice_paragraph\">Skewed to the left</p>","<p class=\"choice_paragraph\">Skewed to the right</p>","<p class=\"choice_paragraph\">Symmetric</p>","<p class=\"choice_paragraph\">Bimodal</p>","<p class=\"choice_paragraph\">Uniform</p>"],"answer":1}]