[{"id":"VH927302","type":"mcq","stimulusHtml":"<p class=\"stem_paragraph\">The life span of a battery is the amount of time the battery will last. The distribution of life span for a certain type of battery is approximately normal with mean 2.5 hours and standard deviation 0.25 hour. Suppose one battery will be selected at random. Which of the following is closest to the probability that the selected battery will have a life span of at most 2.1 hours?</p>\n","rubricRef":"VH927302_rubric","choicesHtml":["<p class=\"choice_paragraph\">0.055</p>","<p class=\"choice_paragraph\">0.110</p>","<p class=\"choice_paragraph\">0.445</p>","<p class=\"choice_paragraph\">0.890</p>","<p class=\"choice_paragraph\">0.945</p>"],"answer":0}]