[{"id":"FT543994","type":"mcq","stimulusHtml":"<p>According to Xiaoming, one advantage of practicing Taiji is</p>","features":[{"type":"sharedpassage","html":"<p>You will listen to a selection in Chinese. After listening to the selection, choose the response that is best according to the selection.</p>\n\n<p><strong>School conversation</strong></p>\n\n<p><span class=\"learnosity-feature\" data-player=\"bar\" data-simplefeature_id=\"_999bb58eadfba205927dbb36498a9f1b\" data-src=\"https://assets.learnosity.com/organisations/537/media.academicmerit.com/a5ba7d4fdbe560f22a44cd4b87c3c86a/original.mp3\" data-type=\"audioplayer\"></span></p>\n"}],"choicesHtml":["<p>learning self-defense</p>","<p>meeting local people in the park</p>","<p>becoming a better Chinese teacher</p>","<p>gaining a better understanding of Chinese culture</p>"],"answer":2}]