[{"id":"VR030963","type":"mcq","stimulusHtml":"<div><include href=\"../Passage/VR030956.qti.xml\" xmlns:xi=\"http://www.w3.org/2001/XInclude\"></include></div><p class=\"stem_paragraph\">Which of the following items does the man mention that he must take care of?</p>\n","rubricRef":"VR030963_rubric","features":[{"type":"sharedpassage","html":"<div class=\"stimulus_reference\" xmlns=\"http://www.imsglobal.org/xsd/apip/apipv1p0/qtiitem/imsqti_v2p2\" xmlns:xsi=\"http://www.w3.org/2001/XMLSchema-instance\"><div class=\"multimedia_script\"><div class=\"scene scene_type:listening\"><div class=\"displayed_content\"><div class=\"title\"><p class=\"title_line passage-title\">School Conversation</p><div class=\"subtitle\"><p class=\"title_line author\">Selection plays one time.</p></div></div></div><span class=\"sound_script\"><p><span class=\"learnosity-feature\" data-player=\"bar\" data-simplefeature_id=\"_04e0742f0b1221062b37b35972c8f8b2\" data-src=\"https://assets.learnosity.com/organisations/537/VR030956.a01.mp3\" data-type=\"audioplayer\"></span></p><p><span class=\"learnosity-feature\" data-player=\"bar\" data-simplefeature_id=\"_04e0742f0b1221062b37b35972c8f8b2\" data-src=\"https://assets.learnosity.com/organisations/537/VR030956.a03.mp3\" data-type=\"audioplayer\"></span></p><p><span class=\"learnosity-feature\" data-player=\"bar\" data-simplefeature_id=\"_04e0742f0b1221062b37b35972c8f8b2\" data-src=\"https://assets.learnosity.com/organisations/537/VR030956.a02.mp3\" data-type=\"audioplayer\"></span></p><span class=\"pause time_duration:1\"></span></span></div></div></div>"}],"choicesHtml":["<p class=\"choice_paragraph\">Doing lots of homework</p>","<p class=\"choice_paragraph\">Cleaning up his room</p>","<p class=\"choice_paragraph\">Taking care of his younger siblings</p>","<p class=\"choice_paragraph\">Finishing college applications</p>"],"answer":3}]