[{"id":"VH911442","type":"mcq","stimulusHtml":"<div>\n<div class=\"stimulus_reference\">\n<div class=\"standalone_image\"><img alt=\"The figure presents a rectangular circuit with middle vertical branch. The left side of the circuit has a battery. The right side has a resistor labeled R sub 2 equals R and another resistor underneath labeled R sub 3 equals 2 R. The middle vertical branch has a resistor labeled R sub 1 equals 2 R.\" height=\"105\" src=\"https://assets.learnosity.com/organisations/537/VH911442.g01.png\" width=\"225\" /></div>\n</div>\n</div>\n\n<p class=\"stem_paragraph\">The circuit above shows an ideal battery connected to three resistors. Which of the following correctly ranks the potential difference, <span class=\"math_expression\"><span aria-label=\"delta\"><math alttext=\"delta\" overflow=\"scroll\"><mstyle><mrow><mi mathvariant=\"normal\">Δ</mi><mo>⁢</mo></mrow></mstyle></math></span></span><span class=\"math_expression\"><span aria-label=\"V\"><math alttext=\"V\" overflow=\"scroll\"><mstyle><mrow><mi>V</mi></mrow></mstyle></math></span></span>, across the different resistors?</p>\n","rubricRef":"VH911442_rubric","choicesHtml":["<p class=\"choice_paragraph\"><span class=\"math_expression\"><span aria-label=\"delta V sub 1 is greater than delta V sub 3, which is greater than delta V sub 2\"><math alttext=\"delta V sub 1 is greater than delta V sub 3, which is greater than delta V sub 2\" overflow=\"scroll\"><mstyle><mrow><msub><mrow><mi mathvariant=\"normal\">Δ</mi><mi>V</mi></mrow><mrow><mn>1</mn><mo>⁢</mo></mrow></msub><mo>&gt;</mo><msub><mrow><mi mathvariant=\"normal\">Δ</mi><mi>V</mi></mrow><mrow><mn>3</mn></mrow></msub><mo>&gt;</mo><msub><mrow><mi mathvariant=\"normal\">Δ</mi><mi>V</mi></mrow><mrow><mn>2</mn></mrow></msub></mrow></mstyle></math></span></span></p>","<p class=\"choice_paragraph\"><span class=\"math_expression\"><span aria-label=\"delta V sub 1 is equal to delta V sub 3, which is greater than delta V sub 2\"><math alttext=\"delta V sub 1 is equal to delta V sub 3, which is greater than delta V sub 2\" overflow=\"scroll\"><mstyle><mrow><msub><mrow><mi mathvariant=\"normal\">Δ</mi><mi>V</mi></mrow><mrow><mn>1</mn></mrow></msub><mo>=</mo><msub><mrow><mi mathvariant=\"normal\">Δ</mi><mi>V</mi></mrow><mrow><mn>3</mn></mrow></msub><mo>&gt;</mo><msub><mrow><mi mathvariant=\"normal\">Δ</mi><mi>V</mi></mrow><mrow><mn>2</mn></mrow></msub></mrow></mstyle></math></span></span></p>","<p class=\"choice_paragraph\"><span class=\"math_expression\"><span aria-label=\"delta V sub 1 is equal to delta V sub 2, which is greater than delta V sub 3\"><math alttext=\"delta V sub 1 is equal to delta V sub 2, which is greater than delta V sub 3\" overflow=\"scroll\"><mstyle><mrow><mi mathvariant=\"normal\">Δ</mi><msub><mrow><mi>V</mi></mrow><mrow><mn>1</mn></mrow></msub><mo>=</mo><mi mathvariant=\"normal\">Δ</mi><msub><mrow><mi>V</mi></mrow><mrow><mn>2</mn></mrow></msub><mo>&gt;</mo><mi mathvariant=\"normal\">Δ</mi><msub><mrow><mi>V</mi></mrow><mrow><mn>3</mn></mrow></msub></mrow></mstyle></math></span></span></p>","<p class=\"choice_paragraph\"><span class=\"math_expression\"><span aria-label=\"delta V sub 1 is greater than delta V sub 2, which is equal to delta V sub 3\"><math alttext=\"delta V sub 1 is greater than delta V sub 2, which is equal to delta V sub 3\" overflow=\"scroll\"><mstyle><mrow><msub><mrow><mi mathvariant=\"normal\">Δ</mi><mi>V</mi></mrow><mrow><mn>1</mn></mrow></msub><mo>&gt;</mo><msub><mrow><mi mathvariant=\"normal\">Δ</mi><mi>V</mi></mrow><mrow><mn>2</mn></mrow></msub><mo>=</mo><msub><mrow><mi mathvariant=\"normal\">Δ</mi><mi>V</mi></mrow><mrow><mn>3</mn></mrow></msub></mrow></mstyle></math></span></span></p>","<p class=\"choice_paragraph\"><span class=\"math_expression\"><span aria-label=\"delta V sub 2 is greater than delta V sub 1, which is equal to delta V sub 3\"><math alttext=\"delta V sub 2 is greater than delta V sub 1, which is equal to delta V sub 3\" overflow=\"scroll\"><mstyle><mrow><msub><mrow><mi mathvariant=\"normal\">Δ</mi><mi>V</mi></mrow><mrow><mn>2</mn></mrow></msub><mo>&gt;</mo><msub><mrow><mi mathvariant=\"normal\">Δ</mi><mi>V</mi></mrow><mrow><mn>1</mn></mrow></msub><mo>=</mo><msub><mrow><mi mathvariant=\"normal\">Δ</mi><mi>V</mi></mrow><mrow><mn>3</mn></mrow></msub></mrow></mstyle></math></span></span></p>"],"answer":0}]