[{"id":"VR802589","type":"mcq","stimulusHtml":"<div><div class=\"stimulus_reference\"><div class=\"standalone_image\"><img alt=\"The figure shows a circular loop of wire of radius a. A battery is on the upper part of the wire loop.\" src=\"https://assets.learnosity.com/organisations/578/VR802589.g01.svg\"/></div></div></div><p class=\"stem_paragraph\">A battery produces a current within a circular loop of wire of radius <span class=\"math_expression\"><span aria-label=\"a\"><math alttext=\"a\" display=\"inline\" overflow=\"scroll\"><mi>a</mi></math></span></span> and total resistance <span class=\"math_expression\"><span aria-label=\"R\"><math alttext=\"R\" display=\"inline\" overflow=\"scroll\"><mi>R</mi></math></span></span>. The magnetic field at the center of the loop has magnitude <span class=\"math_expression\"><span aria-label=\"B sub 0\"><math alttext=\"B sub 0\" display=\"inline\" overflow=\"scroll\"><msub><mi>B</mi><mn>0</mn></msub></math></span></span>. If the wire was longer such that the radius of the loop was doubled with the same battery attached, what would be the magnitude of the magnetic field produced at the center of the loop?</p>\n","rubricRef":"VR802589_rubric","choicesHtml":["<p class=\"choice_paragraph\"><span class=\"math_expression\"><span aria-label=\"one fourth B sub 0\"><math alttext=\"one fourth B sub 0\" display=\"inline\" overflow=\"scroll\"><mfrac><mn>1</mn><mn>4</mn></mfrac><msub><mi>B</mi><mn>0</mn></msub></math></span></span></p>","<p class=\"choice_paragraph\"><span class=\"math_expression\"><span aria-label=\"one half B sub 0\"><math alttext=\"one half B sub 0\" display=\"inline\" overflow=\"scroll\"><mfrac><mn>1</mn><mn>2</mn></mfrac><msub><mi>B</mi><mn>0</mn></msub></math></span></span></p>","<p class=\"choice_paragraph\"><span class=\"math_expression\"><span aria-label=\"B sub 0\"><math alttext=\"B sub 0\" display=\"inline\" overflow=\"scroll\"><msub><mi>B</mi><mn>0</mn></msub></math></span></span></p>","<p class=\"choice_paragraph\"><span class=\"math_expression\"><span aria-label=\"2 B sub 0\"><math alttext=\"2 B sub 0\" display=\"inline\" overflow=\"scroll\"><mn>2</mn><msub><mi>B</mi><mn>0</mn></msub></math></span></span></p>"],"answer":0}]