[{"id":"VH965814","type":"mcq","stimulusHtml":"<p class=\"stem_paragraph\">Which of the following pairs of countries have nationalized oil resources but have recently allowed private companies to invest in oil extraction to increase production?</p>\n","rubricRef":"VH965814_rubric","choicesHtml":["<p class=\"choice_paragraph\">Mexico and Nigeria</p>","<p class=\"choice_paragraph\">Russia and Iran</p>","<p class=\"choice_paragraph\">The United Kingdom and Russia</p>","<p class=\"choice_paragraph\">Iran and China</p>"],"answer":0}]