[{"id":"FT560988_rubric_category_0","type":"custom","title":"General","stimulusHtml":"<p><strong>1 point is earned for:</strong> sets 1 - 5sin y = 0</p><p><strong>2 points are earned for:</strong> y-coordinate </p><p>1 - 5sin y = 0  </p><p>y = 0.201, 6.485 (or 6.484), 9.223 </p>","labels":["0 points","1 point","2 points","3 points"],"values":[0,1,2,3],"maxScores":[3,3,3,3],"descriptions":["<p>The student response earns one of the following points:</p><p><strong>1 point is earned for:</strong> sets 1 - 5sin y = 0</p><p><strong>2 points are earned for:</strong> y-coordinate</p><p>1 - 5sin y = 0</p><p>y = 0.201, 6.485 (or 6.484), 9.223</p>","<p>The student response earns none of the following points:</p><p><strong>1 point is earned for:</strong> sets 1 - 5sin y = 0</p><p><strong>2 points are earned for:</strong> y-coordinate</p><p>1 - 5sin y = 0</p><p>y = 0.201, 6.485 (or 6.484), 9.223</p>","<p>The student response earns two of the following points:</p><p><strong>1 point is earned for:</strong> sets 1 - 5sin y = 0</p><p><strong>2 points are earned for:</strong> y-coordinate</p><p>1 - 5sin y = 0</p><p>y = 0.201, 6.485 (or 6.484), 9.223</p>","<p>The student response earns all of the following points:</p><p><strong>1 point is earned for:</strong> sets 1 - 5sin y = 0</p><p><strong>2 points are earned for:</strong> y-coordinate</p><p>1 - 5sin y = 0</p><p>y = 0.201, 6.485 (or 6.484), 9.223</p>"]}]