[{"id":"VR781564","type":"mcq","stimulusHtml":"<div>\n<div class=\"stimulus_reference\">\n<div>Which of the following correctly ranks the orbital periods <span class=\"math_expression\"><span aria-label=\"T sub A\" role=\"math\"><math alttext=\"T sub A\" overflow=\"scroll\"><msub><mi>T</mi><mtext mathvariant=\"italic\">A</mtext></msub></math></span></span>, <span class=\"math_expression\"><span aria-label=\"T sub B\" role=\"math\"><math alttext=\"T sub B\" overflow=\"scroll\"><msub><mi>T</mi><mi>B</mi></msub></math></span></span>, <span class=\"math_expression\"><span aria-label=\"T sub C\" role=\"math\"><math alttext=\"T sub C\" overflow=\"scroll\"><msub><mi>T</mi><mi>C</mi></msub></math></span></span>, and <span class=\"math_expression\"><span aria-label=\"T sub D\" role=\"math\"><math alttext=\"T sub D\" overflow=\"scroll\"> <msub> <mi>T</mi> <mi>D</mi> </msub> </math></span></span> of satellites <span class=\"math_expression\"><span aria-label=\"A\" role=\"math\"><math alttext=\"A\" overflow=\"scroll\"><mi mathvariant=\"normal\">A</mi></math></span></span>, <span class=\"math_expression\"><span aria-label=\"B\" role=\"math\"><math alttext=\"B\" overflow=\"scroll\"><mi mathvariant=\"normal\">B</mi></math></span></span>, <span class=\"math_expression\"><span aria-label=\"C\" role=\"math\"><math alttext=\"C\" overflow=\"scroll\"><mi mathvariant=\"normal\">C</mi></math></span></span>, and <span class=\"math_expression\"><span aria-label=\"D\" role=\"math\"><math alttext=\"D\" overflow=\"scroll\"><mi mathvariant=\"normal\">D</mi></math></span></span>, respectively, from least to greatest?</div>\n</div>\n</div>\n","rubricRef":"VR781564_rubric","features":[{"type":"sharedpassage","html":"<p class=\"stem_paragraph\">Four satellites <span class=\"math_expression\"><span aria-label=\"A\" role=\"math\"><math alttext=\"A\" overflow=\"scroll\"><mi mathvariant=\"normal\">A</mi></math></span></span>, <span class=\"math_expression\"><span aria-label=\"B\" role=\"math\"><math alttext=\"B\" overflow=\"scroll\"><mi mathvariant=\"normal\">B</mi></math></span></span>, <span class=\"math_expression\"><span aria-label=\"C\" role=\"math\"><math alttext=\"C\" overflow=\"scroll\"><mi mathvariant=\"normal\">C</mi></math></span></span>, and <span class=\"math_expression\"><span aria-label=\"D\" role=\"math\"><math alttext=\"D\" overflow=\"scroll\"><mi mathvariant=\"normal\">D</mi></math></span></span> have circular orbits about Planets <span class=\"math_expression\"><span aria-label=\"X\" role=\"math\"><math alttext=\"X\" overflow=\"scroll\"><mi mathvariant=\"normal\">X</mi></math></span></span> and <span class=\"math_expression\"><span aria-label=\"Y\" role=\"math\"><math alttext=\"Y\" overflow=\"scroll\"> <mi mathvariant=\"normal\">Y</mi> </math></span></span>, as shown. Planet <span class=\"math_expression\"><span aria-label=\"Y\" role=\"math\"><math alttext=\"Y\" overflow=\"scroll\"><mi mathvariant=\"normal\">Y</mi></math></span></span> has twice the mass of Planet <span class=\"math_expression\"><span aria-label=\"X\" role=\"math\"><math alttext=\"X\" overflow=\"scroll\"><mi mathvariant=\"normal\">X</mi></math></span></span>. Satellite <span class=\"math_expression\"><span aria-label=\"A\" role=\"math\"><math alttext=\"A\" overflow=\"scroll\"><mi mathvariant=\"normal\">A</mi></math></span></span> has mass <span class=\"math_expression\"><span aria-label=\"lowercase m\" role=\"math\"><math alttext=\"lowercase m\" overflow=\"scroll\"><mi>m</mi></math></span></span> and orbits a distance <span class=\"math_expression\"><span aria-label=\"R\" role=\"math\"><math alttext=\"R\" overflow=\"scroll\"><mi>R</mi></math></span></span> from the center of Planet <span class=\"math_expression\"><span aria-label=\"X\" role=\"math\"><math alttext=\"X\" overflow=\"scroll\"><mi mathvariant=\"normal\">X</mi></math></span></span>. Satellites <span class=\"math_expression\"><span aria-label=\"B\" role=\"math\"><math alttext=\"B\" overflow=\"scroll\"><mi mathvariant=\"normal\">B</mi></math></span></span> and <span class=\"math_expression\"><span aria-label=\"C\" role=\"math\"><math alttext=\"C\" overflow=\"scroll\"><mi mathvariant=\"normal\">C</mi></math></span></span> have masses <span class=\"math_expression\"><span aria-label=\"lowercase m\" role=\"math\"><math alttext=\"lowercase m\" overflow=\"scroll\"><mi>m</mi></math></span></span> and <span class=\"math_expression\"><span aria-label=\"2 lowercase m\" role=\"math\"><math alttext=\"2 lowercase m\" overflow=\"scroll\"><mn>2</mn><mi>m</mi></math></span></span>, respectively, and orbit a distance <span class=\"math_expression\"><span aria-label=\"2 R\" role=\"math\"><math alttext=\"2 R\" overflow=\"scroll\"><mn>2</mn><mi>R</mi></math></span></span> from the center of Planet&nbsp;<span class=\"math_expression\"><span aria-label=\"X\" role=\"math\"><math alttext=\"X\" overflow=\"scroll\"><mi mathvariant=\"normal\">X</mi></math></span></span>. Satellite <span class=\"math_expression\"><span aria-label=\"D\" role=\"math\"><math alttext=\"D\" overflow=\"scroll\"><mi mathvariant=\"normal\">D</mi></math></span></span> has mass <span class=\"math_expression\"><span aria-label=\"lowercase m\" role=\"math\"><math alttext=\"lowercase m\" overflow=\"scroll\"><mi>m</mi></math></span></span> and orbits Planet <span class=\"math_expression\"><span aria-label=\"Y\" role=\"math\"><math alttext=\"Y\" overflow=\"scroll\"><mi mathvariant=\"normal\">Y</mi></math></span></span> in a distance <span class=\"math_expression\"><span aria-label=\"2 R\" role=\"math\"><math alttext=\"2 R\" overflow=\"scroll\"><mn>2</mn><mi>R</mi></math></span></span> from the center of the Planet <span class=\"math_expression\"><span aria-label=\"X\" role=\"math\"><math alttext=\"X\" overflow=\"scroll\"><mtext>X</mtext></math></span></span>.</p>\n\n<div class=\"standalone_image\"><img alt=\"The figure shows 4 satellites, labeled A through D, in circular orbits about 2 planets, labeled X and Y. Satellite A orbits a distance R from the center of Planet X. Satellites B and C each orbit a distance 2 R from the center of Planet X, and they are on opposite sides of the planet. Satellite D orbits a distance 2 R from the center of the Planet Y.\" src=\"https://assets.learnosity.com/organisations/578/VR781564.g05.svg\" /></div>\n"}],"choicesHtml":["<p class=\"choice_paragraph\"><span class=\"math_expression\"><span aria-label=\"T sub A is less than T sub D, which is less than, open parenthesis, T sub B equals T sub C, close parenthesis\"><math alttext=\"T sub A is less than T sub D, which is less than, open parenthesis, T sub B equals T sub C, close parenthesis\" overflow=\"scroll\"><mstyle displaystyle=\"true\"><msub><mi>T</mi><mi>A</mi></msub><mo>&lt;</mo><msub><mi>T</mi><mi>D</mi></msub><mo>&lt;</mo><mo stretchy=\"false\">(</mo><msub><mi>T</mi><mi>B</mi></msub><mo>=</mo><msub><mi>T</mi><mi>C</mi></msub><mo stretchy=\"false\">)</mo></mstyle></math></span></span></p>","<p class=\"choice_paragraph\"><span class=\"math_expression\"><span aria-label=\"T sub A is less than, open parenthesis, T sub B equals T sub C, which equals T sub D, close parenthesis\"><math alttext=\"T sub A is less than, open parenthesis, T sub B equals T sub C, which equals T sub D, close parenthesis\" overflow=\"scroll\"><mstyle displaystyle=\"true\"><msub><mi>T</mi><mi>A</mi></msub><mo>&lt;</mo><mrow><mo>(</mo><msub><mi>T</mi><mi>B</mi></msub><mo>=</mo><msub><mi>T</mi><mi>C</mi></msub><mo>=</mo><msub><mi>T</mi><mi>D</mi></msub><mo>)</mo></mrow></mstyle></math></span></span></p>","<p class=\"choice_paragraph\"><span class=\"math_expression\"><span aria-label=\"T sub D is less than T sub A, which is less than, open parenthesis, T sub B equals T sub C, close parenthesis\"><math alttext=\"T sub D is less than T sub A, which is less than, open parenthesis, T sub B equals T sub C, close parenthesis\" overflow=\"scroll\"><mstyle displaystyle=\"true\"><msub><mi>T</mi><mi>D</mi></msub><mo>&lt;</mo><msub><mi>T</mi><mi>A</mi></msub><mo>&lt;</mo><mo stretchy=\"false\">(</mo><msub><mi>T</mi><mi>B</mi></msub><mo>=</mo><msub><mi>T</mi><mi>C</mi></msub><mo stretchy=\"false\">)</mo></mstyle></math></span></span></p>","<p class=\"choice_paragraph\"><span class=\"math_expression\"><span aria-label=\"T sub D is less than T sub A, which is less than, T sub B, which is less than T sub C\"><math alttext=\"T sub D is less than T sub A, which is less than, T sub B, which is less than T sub C\" overflow=\"scroll\"><mstyle displaystyle=\"true\"><msub><mi>T</mi><mi>D</mi></msub><mo>&lt;</mo><msub><mi>T</mi><mi>A</mi></msub><mo>&lt;</mo><msub><mi>T</mi><mi>B</mi></msub><mo>&lt;</mo><msub><mi>T</mi><mi>C</mi></msub></mstyle></math></span></span></p>"],"answer":0}]