[{"id":"VH920876","type":"mcq","stimulusHtml":"<p class=\"stem_paragraph\">Consider the following class definition.</p><div class=\"standalone_code style:1\"><p class=\"code_line indent:0\">public class ItemInventory</p><p class=\"code_line indent:0\">{</p><p class=\"code_line indent:3\">private int numItems;</p><p class=\"code_line indent:0\"></p><p class=\"code_line indent:3\">public ItemInventory(int num)</p><p class=\"code_line indent:3\">{</p><p class=\"code_line indent:6\">numItems = num;</p><p class=\"code_line indent:3\">}</p><p class=\"code_line indent:0\"></p><p class=\"code_line indent:3\">public updateItems(int newNum)</p><p class=\"code_line indent:3\">{</p><p class=\"code_line indent:6\">numItems = newNum;</p><p class=\"code_line indent:3\">}</p><p class=\"code_line indent:0\">}</p></div><p class=\"stem_paragraph\">Which of the following best identifies the reason the class does not compile?</p>\n","rubricRef":"VH920876_rubric","choicesHtml":["<p class=\"choice_paragraph\">The constructor header is missing a return type.</p>","<p class=\"choice_paragraph\">The <span class=\"inline_code\">updateItems</span> method is missing a return type.</p>","<p class=\"choice_paragraph\">The <span class=\"inline_code\">updateItems</span> method should not have a parameter.</p>","<p class=\"choice_paragraph\">The instance variable <span class=\"inline_code\">numItems</span> should be <span class=\"inline_code\">public</span> instead of <span class=\"inline_code\">private</span>.</p>"],"answer":1}]