[{"id":"VH920229","type":"mcq","stimulusHtml":"<p class=\"stem_paragraph\">Consider the following class definition.</p><div class=\"standalone_code style:1\"><p class=\"code_line\">public class Toy</p><p class=\"code_line\">{</p><p class=\"code_line indent:3\">private int yearFirstSold;</p><p class=\"code_line\"></p><p class=\"code_line indent:3\">public int getYearFirstSold()</p><p class=\"code_line indent:3\">{</p><p class=\"code_line indent:6\">return yearFirstSold;</p><p class=\"code_line indent:3\">}</p><p class=\"code_line\"></p><p class=\"code_line indent:3\">/* <span class=\"formatted_text font_style:normal font_variant:normal font_weight:normal\">There may be instance variables, constructors, and other methods not shown.</span> */</p><p class=\"code_line\">}</p></div><p class=\"stem_paragraph\">The following code segment, which appears in a class other than <span class=\"inline_code\">Toy</span>,<span> </span>prints the year each <span class=\"inline_code\">Toy</span> object in <span class=\"inline_code\">toyArray</span> was first sold by its manufacturer. Assume that <span class=\"inline_code\">toyArray</span> is a properly declared and initialized array of <span class=\"inline_code\">Toy</span> objects.</p><div class=\"standalone_code style:1\"><p class=\"code_line indent:0\">for (Toy k : toyArray)</p><p class=\"code_line indent:0\">{</p><p class=\"code_line indent:3\">System.out.println(k.getYearFirstSold());</p><p class=\"code_line indent:0\">}</p></div><p class=\"stem_paragraph\">Which of the following could be used in place of the given code segment to produce the same output?</p><div class=\"standalone_code style:1\"><div class=\"title\"><p class=\"title_line passage-title\">I.</p></div><p class=\"code_line indent:0\">for (int k = 0; k &lt; toyArray.length; k++)</p><p class=\"code_line indent:0\">{</p><p class=\"code_line indent:3\">System.out.println(getYearFirstSold(k));</p><p class=\"code_line indent:0\">}</p></div><div class=\"standalone_code style:1\"><div class=\"title\"><p class=\"title_line passage-title\">II.</p></div><p class=\"code_line indent:0\">for (int k = 0; k &lt; toyArray.length; k++)</p><p class=\"code_line indent:0\">{</p><p class=\"code_line indent:3\">System.out.println(k.getYearFirstSold());</p><p class=\"code_line indent:0\">}</p></div><div class=\"standalone_code style:1\"><div class=\"title\"><p class=\"title_line passage-title\">III.</p></div><p class=\"code_line indent:0\">for (int k = 0; k &lt; toyArray.length; k++)</p><p class=\"code_line indent:0\">{</p><p class=\"code_line indent:3\">System.out.println(toyArray[k].getYearFirstSold());</p><p class=\"code_line indent:0\">}</p></div>\n","rubricRef":"VH920229_rubric","choicesHtml":["<p class=\"choice_paragraph\">II only</p>","<p class=\"choice_paragraph\">III only</p>","<p class=\"choice_paragraph\">I and II</p>","<p class=\"choice_paragraph\">II and III</p>"],"answer":2}]