[{"id":"XJI000005","type":"mcq","stimulusHtml":"<p class=\"dap_body\">What is printed as a result of executing this code segment?</p>","features":[{"type":"sharedpassage","html":"<div class=\"stimulus_reference\"><p class=\"dap_body\">Consider the following code segment.</p><p class=\"dap_body\"> </p><pre><code class=\"language-plaintext\">int value = 100;\nwhile (value % 5 == 0)\n{\n   value /= 2;\n}\nSystem.out.println(value);</code></pre></div>"}],"choicesHtml":["<pre><code class=\"language-plaintext\">12</code></pre>","<pre><code class=\"language-plaintext\">13</code></pre>","<pre><code class=\"language-plaintext\">25</code></pre>","<pre><code class=\"language-plaintext\">100</code></pre>"],"answer":"1717077147749.6848"}]