[{"id":"FT5686","type":"mcq","stimulusHtml":"<p>“In the year of our Lord 1315, hunger grew in the land. Entering the city we consider ‘them that are consumed with famine’ when we see the poor and needy, crushed with hunger, lying stiff and dead in the wards and streets.”</p>\n\n<p class=\"text-right\">Johannes de Trokelowe, English monk, fourteenth century C.E.</p>\n\n<p>What mostly likely caused the famine described above?</p>\n","choicesHtml":["<p>The Little Ice Age</p>","<p>Desertification</p>","<p>The Crusades</p>","<p>Monsoon flooding</p>"],"answer":-1}]