[{"id":"VH990772","type":"mcq","stimulusHtml":"<div><include href=\"../Passage/VH990770.qti.xml\" xmlns:xi=\"http://www.w3.org/2001/XInclude\"></include></div><p class=\"stem_paragraph\">Which of the following best explains the cause of the historical development depicted in the image?</p>\n","rubricRef":"VH990772_rubric","features":[{"type":"sharedpassage","html":"<div class=\"stimulus_reference\" xmlns=\"http://www.imsglobal.org/xsd/apip/apipv1p0/qtiitem/imsqti_v2p2\" xmlns:xsi=\"http://www.w3.org/2001/XMLSchema-instance\">\n<div class=\"passage\">\n<div class=\"prose style:1\">\n<div class=\"standalone_image\"><img alt=\"The figure presents a photograph of a woman using small industrial tools at a workbench. She is surrounded by six other women who are watching her closely. The women are wearing protective goggles and have tied back their hair using scarves.\" height=\"271\" src=\"https://assets.learnosity.com/organisations/537/VH990770.g01.png\" width=\"340\" /></div>\n\n<p class=\"passage_para\">“Secretaries, housewives, waitresses, women from all over central Florida are getting into vocational schools to learn war work. Typical are these in the Daytona Beach branch of the Volusia County vocational school.” Office of War Information, 1942.</p>\n<span class=\"mandatory_credit_line\">Courtesy of the National Archives</span></div>\n</div>\n</div>\n"}],"choicesHtml":["<p class=\"choice_paragraph\">Workforce shortages led to calls for women to perform jobs previously reserved for men.</p>","<p class=\"choice_paragraph\">Americans developed more liberal attitudes about the proper role of women in the workforce.</p>","<p class=\"choice_paragraph\">New Deal policies encouraged women to pursue educational opportunities in order to stimulate the economy.</p>","<p class=\"choice_paragraph\">White women generally engaged in vocational labor because of the persistence of racism by employers.</p>"],"answer":0}]