[{"id":"VR856153","type":"mcq","stimulusHtml":"<div><div class=\"stimulus_reference\"><div class=\"standalone_image\"><img alt=\"The figure shows a diagram consisting of, from left to right along a horizontal line, an object pointing upward and a convex mirror. The mirror has two focal points on either side of the horizontal line that are the same distance from the mirror, and farther away from the mirror than the object.\" src=\"https://assets.learnosity.com/organisations/578/VR856153.g01.svg\"/></div></div></div><p class=\"stem_paragraph\">The figure shows a lens, the locations of the two focal points for the lens, and an object (represented by the upward arrow). Which of the following correctly describes the image formed by the lens?</p>\n","rubricRef":"VR856153_rubric","choicesHtml":["<p class=\"choice_paragraph\">The image is upright and real.</p>","<p class=\"choice_paragraph\">The image is upright and virtual.</p>","<p class=\"choice_paragraph\">The image is inverted and real.</p>","<p class=\"choice_paragraph\">The image is inverted and virtual.</p>"],"answer":1}]