[{"id":"VH922391","type":"mcq","stimulusHtml":"<div>\n<div class=\"stimulus_reference\">\n<div class=\"standalone_image\"><img alt=\"One whole note notated in treble clef. They key signature has one sharp. The pitch notated is D5.\" height=\"99\" src=\"https://assets.learnosity.com/organisations/537/VH922391.g03.png\" width=\"280\" /></div>\n</div>\n</div>\n\n<p class=\"stem_paragraph\">Which symbol raises the written pitch one whole step?</p>\n","rubricRef":"VH922391_rubric","choicesHtml":["<p class=\"choice_paragraph\">Flat</p>","<p class=\"choice_paragraph\">Natural</p>","<p class=\"choice_paragraph\">Sharp</p>","<p class=\"choice_paragraph\">Double sharp</p>"],"answer":3}]