[{"id":"VH920497","type":"mcq","stimulusHtml":"<div><include href=\"../Passage/VH920483.qti.xml\" xmlns:xi=\"http://www.w3.org/2001/XInclude\"></include></div><p class=\"stem_paragraph\">In relation to the opening key (measures 1-16), the trio (measures 17-32) is in which of the following keys?</p>\n","rubricRef":"VH920497_rubric","features":[{"type":"sharedpassage","html":"<div class=\"stimulus_reference\" xmlns=\"http://www.imsglobal.org/xsd/apip/apipv1p0/qtiitem/imsqti_v2p2\" xmlns:xsi=\"http://www.w3.org/2001/XMLSchema-instance\">\n<p class=\"lead_in\">The following question is based on the excerpt below.</p>\n\n<div class=\"standalone_image\"><img alt=\"The figure presents thirty-two measures of music for piano on a grand staff. The key signature has one flat to start and changes to two flats at measure seventeen. The time signature is 3/4.\" height=\"910\" src=\"https://assets.learnosity.com/organisations/537/VH920483.g04.png\" width=\"700\" /></div>\n</div>\n"}],"choicesHtml":["<p class=\"choice_paragraph\">The parallel minor key</p>","<p class=\"choice_paragraph\">The relative minor key</p>","<p class=\"choice_paragraph\">A closely related key</p>","<p class=\"choice_paragraph\">A distantly related key</p>"],"answer":2}]