[{"id":"VH952203","type":"mcq","stimulusHtml":"<div><div class=\"stimulus_reference\"><span class=\"sound_script\"><span class=\"learnosity-feature\" data-player=\"bar\" data-src=\"https://assets.learnosity.com/organisations/537/VH952203.a01.mp3\" data-type=\"audioplayer\"></span></span></div></div><p class=\"stem_paragraph\">The excerpt ends with which of the following cadences?</p>\n","rubricRef":"VH952203_rubric","choicesHtml":["<p class=\"choice_paragraph\">Half cadence</p>","<p class=\"choice_paragraph\">Deceptive cadence</p>","<p class=\"choice_paragraph\">Perfect authentic cadence</p>","<p class=\"choice_paragraph\">Imperfect authentic cadence</p>"],"answer":0}]