[{"id":"VR002391","type":"mcq","stimulusHtml":"<div><include href=\"../Passage/VR002385.qti.xml\" xmlns:xi=\"http://www.w3.org/2001/XInclude\"></include></div><p class=\"stem_paragraph\">The first leading-tone chord tonicizes</p>\n","rubricRef":"VR002391_rubric","features":[{"type":"sharedpassage","html":"<div class=\"stimulus_reference\" xmlns=\"http://www.imsglobal.org/xsd/apip/apipv1p0/qtiitem/imsqti_v2p2\" xmlns:xsi=\"http://www.w3.org/2001/XMLSchema-instance\"><div class=\"multimedia_script\"><div class=\"scene\"><div class=\"displayed_content\"><p class=\"lead_in\">The following question is based on an excerpt you will hear for string quartet. The example includes two secondary leading-tone chords.</p></div><span class=\"sound_script\"><p><span class=\"learnosity-feature\" data-player=\"bar\" data-simplefeature_id=\"_7500709b14e140845ad60eca4ddc3195\" data-src=\"https://assets.learnosity.com/organisations/537/VR002385.a01.mp3\" data-type=\"audioplayer\"></span></p></span></div></div></div>"}],"choicesHtml":["<p class=\"choice_paragraph\"><span class=\"music_roman_numeral\">ⅱ</span></p>","<p class=\"choice_paragraph\"><span class=\"music_roman_numeral\">ⅲ</span></p>","<p class=\"choice_paragraph\"><span class=\"music_roman_numeral\">Ⅳ</span></p>","<p class=\"choice_paragraph\"><span class=\"music_roman_numeral\">Ⅴ</span></p>"],"answer":2}]