[{"id":"VR733236","type":"mcq","stimulusHtml":"<p class=\"stem_paragraph\">If an economy is currently experiencing a decrease in the price level and the banking system has limited reserves, which of the following monetary policy actions can be implemented to reverse the change in the price level in the short run?</p>\n","rubricRef":"VR733236_rubric","choicesHtml":["<p class=\"choice_paragraph\">Increasing the required reserve ratio</p>","<p class=\"choice_paragraph\">Increasing the policy rate</p>","<p class=\"choice_paragraph\">Increasing government spending</p>","<p class=\"choice_paragraph\">Selling bonds on the open market</p>","<p class=\"choice_paragraph\">Buying bonds on the open market</p>"],"answer":4}]